patrick/__init__.py
patrick/cli.py
patrick-0.2.0.dist-info/entry_points.txt
patrick-0.2.0.dist-info/WHEEL
patrick-0.2.0.dist-info/METADATA
patrick-0.2.0.dist-info/RECORD
