Metadata-Version: 2.1
Name: patrick
Version: 0.2.0
License: MIT
Author-email: Patrick Arminio <patrick.arminio@gmail.com>
Requires-Python: >=3.7
Requires-Dist: rich>=12.6.0
Requires-Dist: typer>=0.7.0
